scobra/__init__.py
scobra/analysis/FCA.py
scobra/analysis/FVA.py
scobra/analysis/FluxAnalysis.py
scobra/analysis/FluxSum.py
scobra/analysis/GeometricFBA.py
scobra/analysis/Graph.py
scobra/analysis/MOMA.py
scobra/analysis/Match.py
scobra/analysis/MinSolve.py
scobra/analysis/Pareto.py
scobra/analysis/ROOM.py
scobra/analysis/RWFM.py
scobra/analysis/RWFMSolveMinFlux.py
scobra/analysis/Scan.py
scobra/analysis/__init__.py
scobra/analysis/compare_elements.py
scobra/classes/__init__.py
scobra/classes/concentration.py
scobra/classes/db.py
scobra/classes/fca.py
scobra/classes/flux.py
scobra/classes/fva.py
scobra/classes/matrix.py
scobra/classes/metabolite.py
scobra/classes/model.py
scobra/classes/pareto.py
scobra/classes/reaction.py
scobra/io/Cyc.py
scobra/io/Excel.py
scobra/io/IO.py
scobra/io/Network.py
scobra/io/ScrumPy.py
scobra/io/__init__.py
scobra/manipulation/Reversible.py
scobra/manipulation/__init__.py
scobra-1.1.4.dist-info/METADATA
scobra-1.1.4.dist-info/WHEEL
scobra-1.1.4.dist-info/top_level.txt
scobra-1.1.4.dist-info/RECORD
